pytest_clean_db/__init__.py
pytest_clean_db/connection.py
pytest_clean_db/dialect/__init__.py
pytest_clean_db/dialect/mysql.py
pytest_clean_db/dialect/postgres.py
pytest_clean_db/plugin.py
pytest_clean_db/py.typed
pytest_clean_database-1.0.0.dist-info/LICENSE
pytest_clean_database-1.0.0.dist-info/METADATA
pytest_clean_database-1.0.0.dist-info/WHEEL
pytest_clean_database-1.0.0.dist-info/entry_points.txt
pytest_clean_database-1.0.0.dist-info/RECORD
