Metadata-Version: 2.3
Name: pytest-clean-database
Version: 1.0.0
Summary: A pytest plugin that cleans your database up after every test.
License: MIT
Author: Roman Vlasenko
Author-email: klavionik@gmail.com
Requires-Python: >=3.8
Classifier: Development Status :: 3 - Alpha
Classifier: Framework :: Pytest
Classifier: License :: OSI Approved :: MIT License
Classifier: Programming Language :: Python :: 3
Classifier: Programming Language :: Python :: 3.8
Classifier: Programming Language :: Python :: 3.9
Classifier: Programming Language :: Python :: 3.10
Classifier: Programming Language :: Python :: 3.11
Classifier: Programming Language :: Python :: 3.12
Classifier: Programming Language :: Python :: 3.13
Classifier: Typing :: Typed
Provides-Extra: mysql
Provides-Extra: psql
Requires-Dist: psycopg (>=3.0,<4.0.0) ; extra == "psql"
Requires-Dist: pymysql (>=1.0,<2.0.0) ; extra == "mysql"
Requires-Dist: pytest (>=7.0,<9)
